LICENSE
MANIFEST.in
README.md
requires.txt
setup.py
simple_migrate.py
simple_migrate.egg-info/PKG-INFO
simple_migrate.egg-info/SOURCES.txt
simple_migrate.egg-info/dependency_links.txt
simple_migrate.egg-info/not-zip-safe
simple_migrate.egg-info/requires.txt
simple_migrate.egg-info/top_level.txt