Metadata-Version: 1.1
Name: simple-migrate
Version: 0.0.3
Summary: A simple database migrate tool for flask
Home-page: https://github.com/ncuhome/simple-migrate
Author: ncuhome
Author-email: dev@ncuhome.cn
License: MIT
Platform: UNKNOWN
Classifier: Framework :: Flask
Classifier: Intended Audience :: Developers
Classifier: License :: OSI Approved :: MIT License
Classifier: Operating System :: OS Independent
Classifier: Programming Language :: Python :: 3 :: Only
Classifier: Topic :: Software Development :: Libraries :: Python Modules
